assets/dashboard-01.png
client/dist/bundle.2c17c93ee31da7d3b698.css
client/dist/bundle.f138fad42f9667617133.js
client/dist/bundle.f138fad42f9667617133.js.LICENSE.txt
client/dist/images/.gitkeep
client/dist/index.html
client/dist/scripts/brands.min.js
client/dist/scripts/brands.min.js.LICENSE.txt
client/dist/scripts/fontawesome.min.js
client/dist/scripts/fontawesome.min.js.LICENSE.txt
client/dist/scripts/solid.min.js
client/dist/scripts/solid.min.js.LICENSE.txt
client/dist/webfonts/fa-brands-400.eot
client/dist/webfonts/fa-brands-400.svg
client/dist/webfonts/fa-brands-400.ttf
client/dist/webfonts/fa-brands-400.woff
client/dist/webfonts/fa-brands-400.woff2
client/dist/webfonts/fa-duotone-900.eot
client/dist/webfonts/fa-duotone-900.svg
client/dist/webfonts/fa-duotone-900.ttf
client/dist/webfonts/fa-duotone-900.woff
client/dist/webfonts/fa-duotone-900.woff2
client/dist/webfonts/fa-light-300.eot
client/dist/webfonts/fa-light-300.svg
client/dist/webfonts/fa-light-300.ttf
client/dist/webfonts/fa-light-300.woff
client/dist/webfonts/fa-light-300.woff2
client/dist/webfonts/fa-regular-400.eot
client/dist/webfonts/fa-regular-400.svg
client/dist/webfonts/fa-regular-400.ttf
client/dist/webfonts/fa-regular-400.woff
client/dist/webfonts/fa-regular-400.woff2
client/dist/webfonts/fa-solid-900.eot
client/dist/webfonts/fa-solid-900.svg
client/dist/webfonts/fa-solid-900.ttf
client/dist/webfonts/fa-solid-900.woff
client/dist/webfonts/fa-solid-900.woff2
plsexplain/cli.py
plsexplain/dashboard.py
plsexplain/server.py
plsexplain-0.2.0.dist-info/entry_points.txt
plsexplain-0.2.0.dist-info/LICENSE
plsexplain-0.2.0.dist-info/WHEEL
plsexplain-0.2.0.dist-info/METADATA
plsexplain-0.2.0.dist-info/RECORD
