Metadata-Version: 2.1
Name: plsexplain
Version: 0.2.0
Summary: Create an explainable AI dashboard for your machine learning model.
Home-page: https://wmeints.github.io/plsexplain
License: MIT
Author: Willem Meints
Author-email: willem.meints@gmail.com
Requires-Python: >=3.8,<4.0
Classifier: License :: OSI Approved :: MIT License
Classifier: Programming Language :: Python :: 3
Classifier: Programming Language :: Python :: 3.8
Classifier: Programming Language :: Python :: 3.9
Requires-Dist: aiofiles (>=0.7.0,<0.8.0)
Requires-Dist: click (>=8.0.1,<9.0.0)
Requires-Dist: dalex (>=1.2.0,<2.0.0)
Requires-Dist: fastapi (>=0.65.2,<0.66.0)
Requires-Dist: joblib (>=1.0.1,<2.0.0)
Requires-Dist: pandas (>=1.2.5,<2.0.0)
Requires-Dist: progressbar2 (>=3.53.1,<4.0.0)
Requires-Dist: scikit-learn (>=0.24.2,<0.25.0)
Requires-Dist: tqdm (>=4.61.1,<5.0.0)
Requires-Dist: uvicorn[standard] (>=0.14.0,<0.15.0)
Project-URL: Repository, https://github.com/wmeints/plsexplain
